apetest/__init__.py
apetest/checker.py
apetest/cmdline.py
apetest/control.py
apetest/fetch.py
apetest/plugin/__init__.py
apetest/plugin/checkhtml.py
apetest/plugin/controlcenter.py
apetest/plugin/softfab.py
apetest/referrer.py
apetest/report.py
apetest/request.py
apetest/robots.py
apetest/spider.py
apetest/version.py
apetest/vnuclient.py
apetest/xmlgen.py
apetest-0.1.1.dist-info/entry_points.txt
apetest-0.1.1.dist-info/LICENSE
apetest-0.1.1.dist-info/WHEEL
apetest-0.1.1.dist-info/METADATA
apetest-0.1.1.dist-info/RECORD
