Metadata-Version: 2.1
Name: apetest
Version: 0.1.1
Summary: Smarter-than-monkey testing for web apps
Home-page: https://boxingbeetle.com/tools/ape/
License: BSD-3-Clause
Keywords: webapp,website,test,check,html
Author: Maarten ter Huurne
Author-email: maarten@boxingbeetle.com
Requires-Python: >=3.5,<4.0
Classifier: Development Status :: 3 - Alpha
Classifier: Intended Audience :: Developers
Classifier: License :: OSI Approved :: BSD License
Classifier: Natural Language :: English
Classifier: Operating System :: OS Independent
Classifier: Programming Language :: Python :: 3
Classifier: Programming Language :: Python :: 3.5
Classifier: Programming Language :: Python :: 3.6
Classifier: Programming Language :: Python :: 3.7
Classifier: Topic :: Internet :: WWW/HTTP
Classifier: Topic :: Software Development :: Testing
Requires-Dist: html5validator (>=0.3.1,<0.4.0)
Requires-Dist: lxml (>=4.0,<5.0)
Project-URL: Documentation, https://apedocs.boxingbeetle.com/
Project-URL: Repository, https://github.com/boxingbeetle/apetest
